MANIFEST.in
setup.py
docs/CONTRIBUTORS.txt
docs/HISTORY.txt
docs/LICENSE.ZPL
docs/LICENSE.txt
docs/README.txt
docs/startup.py
src/ztfy/__init__.py
src/ztfy.beaker.egg-info/PKG-INFO
src/ztfy.beaker.egg-info/SOURCES.txt
src/ztfy.beaker.egg-info/dependency_links.txt
src/ztfy.beaker.egg-info/entry_points.txt
src/ztfy.beaker.egg-info/namespace_packages.txt
src/ztfy.beaker.egg-info/not-zip-safe
src/ztfy.beaker.egg-info/requires.txt
src/ztfy.beaker.egg-info/top_level.txt
src/ztfy/beaker/__init__.py
src/ztfy/beaker/configure.zcml
src/ztfy/beaker/interfaces.py
src/ztfy/beaker/meta.zcml
src/ztfy/beaker/metaconfigure.py
src/ztfy/beaker/metadirectives.py
src/ztfy/beaker/session.py
src/ztfy/beaker/browser/__init__.py
src/ztfy/beaker/browser/configure.zcml
src/ztfy/beaker/doctests/README.txt
src/ztfy/beaker/locales/ztfy.beaker.pot
src/ztfy/beaker/locales/en/LC_MESSAGES/ztfy.beaker.mo
src/ztfy/beaker/locales/en/LC_MESSAGES/ztfy.beaker.po
src/ztfy/beaker/locales/en/LC_MESSAGES/ztfy.beaker.po~
src/ztfy/beaker/locales/fr/LC_MESSAGES/ztfy.beaker.mo
src/ztfy/beaker/locales/fr/LC_MESSAGES/ztfy.beaker.po
src/ztfy/beaker/locales/fr/LC_MESSAGES/ztfy.beaker.po~
src/ztfy/beaker/tests/__init__.py
src/ztfy/beaker/tests/test_docs.py
src/ztfy/beaker/tests/test_docstrings.py