Metadata-Version: 1.1
Name: ztfy.beaker
Version: 0.1.0
Summary: Beaker package integration for ZTFY
Home-page: http://hg.ztfy.org/ztfy.beaker
Author: Thierry Florac
Author-email: tflorac@ulthar.net
License: zpl
Keywords: ZTFY beaker session
Platform: UNKNOWN
Classifier: Programming Language :: Python
